<?xml version="1.0" encoding="UTF-8"?>
<microprocessor name="Control (Rocket Composites Export)" description="Info Rocket2MCC" width="5" length="4" id_counter="4" id_counter_node="1" sym1="544" sym2="320" sym3="128" sym4="448" sym5="4088" sym6="2032" sym7="992" sym8="448" sym9="448" sym10="8640" sym11="16704" sym12="64960" sym13="16512" sym14="8192">
	<nodes>
		<n id="1" component_id="4">
			<node label="Output (Comp To Radio)" type="5">
				<position x="2" z="3"/>
			</node>
		</n>
	</nodes>
	<group>
		<data type="1049481524">
			<inputs/>
			<outputs/>
		</data>
		<components/>
		<components_bridge>
			<c type="5">
				<object id="4"/>
			</c>
		</components_bridge>
		<groups/>
		<component_states/>
		<component_bridge_states>
			<c0 id="4"/>
		</component_bridge_states>
		<group_states/>
	</group>
</microprocessor>

